userspacefs/__init__.py
userspacefs/abc.py
userspacefs/fuse_adapter.py
userspacefs/fusepy.py
userspacefs/macos_path_conversion.py
userspacefs/memoryfs.py
userspacefs/path_common.py
userspacefs/py.typed
userspacefs/smbserver.py
userspacefs/stdlibfs.py
userspacefs/util_dumpster.py
userspacefs/webdavserver.py
userspacefs-3.1.1.dist-info/LICENSE
userspacefs-3.1.1.dist-info/METADATA
userspacefs-3.1.1.dist-info/WHEEL
userspacefs-3.1.1.dist-info/top_level.txt
userspacefs-3.1.1.dist-info/RECORD
