Metadata-Version: 2.1
Name: userspacefs
Version: 3.1.1
Summary: Cross-platform user-space file systems for Python
Home-page: https://thelig.ht/code/userspacefs
Author: Rian Hunter
Author-email: rian@alum.mit.edu
License: GPL3
Classifier: Development Status :: 5 - Production/Stable
Classifier: Programming Language :: Python :: 3
Classifier: Topic :: System :: Filesystems
Requires-Python: >=3.11
License-File: LICENSE
Requires-Dist: aiohttp (<4,>=3.9.0)
Requires-Dist: typing-extensions (<5,>=4.9.0)
Requires-Dist: pywin32 ; sys_platform == "win32"
